LICENSE
MANIFEST.in
README.md
requirements.txt
setup.py
jigoku/__init__.py
jigoku/app.py
jigoku.egg-info/PKG-INFO
jigoku.egg-info/SOURCES.txt
jigoku.egg-info/dependency_links.txt
jigoku.egg-info/entry_points.txt
jigoku.egg-info/requires.txt
jigoku.egg-info/top_level.txt
jigoku/client/__init__.py
jigoku/client/scrape_pages.py
jigoku/client/scrape_posts.py
jigoku/constant/__init__.py
jigoku/constant/base.py
jigoku/utils/__init__.py
jigoku/utils/disk.py
jigoku/utils/log.py