Metadata-Version: 2.4
Name: jigoku
Version: 3.0.1
Summary: Bulk downloader for booru imageboards with evil intentions
Home-page: https://github.com/sinkaroid/jigoku
Author: sinkaroid
Author-email: anakmancasan@gmail.com
License: MIT
Project-URL: Discord, https://discord.gg/8wj4vM5hHM
Project-URL: Funding, https://github.com/sponsors/sinkaroid
Project-URL: Issue tracker, https://github.com/sinkaroid/jigoku/issues/new/choose
Project-URL: Documentation, https://github.com/sinkaroid/jigoku/wiki
Keywords: booru,downloaderbulk downloader,mass downloader,gelbooru,rule34,safebooru,xbooru,tbib,realbooru,hypnohub,danbooru,atfbooru,yandere,konachan,konachan.net,lolibooru,e621,e926,paheal
Classifier: Development Status :: 3 - Alpha
Classifier: Intended Audience :: Customer Service
Classifier: License :: OSI Approved :: MIT License
Classifier: Natural Language :: English
Classifier: Operating System :: OS Independent
Classifier: Environment :: Console
Classifier: Programming Language :: Python :: 3.7
Classifier: Programming Language :: Python :: 3.8
Classifier: Programming Language :: Python :: 3.9
Classifier: Programming Language :: Python :: 3.10
Classifier: Topic :: Artistic Software
Classifier: Topic :: Games/Entertainment
Classifier: Topic :: Internet :: WWW/HTTP :: Dynamic Content
Classifier: Topic :: Scientific/Engineering :: Image Processing
License-File: LICENSE
Requires-Dist: requests>=2.32.4
Requires-Dist: inputimeout>=1.0.4
Requires-Dist: beautifulsoup4>=4.13.4
Dynamic: author
Dynamic: author-email
Dynamic: classifier
Dynamic: description
Dynamic: description-content-type
Dynamic: home-page
Dynamic: keywords
Dynamic: license
Dynamic: license-file
Dynamic: project-url
Dynamic: requires-dist
Dynamic: summary
